[
  {
    "id": "69768f0c102c7a06",
    "type": "tab",
    "label": "RFID",
    "disabled": false,
    "info": "",
    "env": []
  },
  {
    "id": "962a006ef3f2f000",
    "type": "mqtt in",
    "z": "69768f0c102c7a06",
    "name": "Get Lock Status",
    "topic": "rfid_status",
    "qos": "2",
    "datatype": "auto-detect",
    "broker": "d1fd3606d78fcb8f",
    "nl": false,
    "rap": true,
    "rh": 0,
    "inputs": 0,
    "x": 160,
    "y": 120,
    "wires": [["e395fac4f263f3d4", "89ac20504f9e3850"]]
  },
  {
    "id": "89ac20504f9e3850",
    "type": "ui_template",
    "z": "69768f0c102c7a06",
    "group": "7b5548eb75bbd6d1",
    "name": "Show lock status",
    "order": 0,
    "width": 0,
    "height": 0,
    "format": "<svg height=\"100\" width=\"100\">\n    <circle \n    cx=\"50\" \n    cy=\"50\" \n    r=\"40\"\n    stroke=\"black\"\n    stroke-width = \"3\"\n    fill=\"{{msg.payload === 'open' ? 'green' : 'red'}}\">\n</svg>",
    "storeOutMessages": true,
    "fwdInMessages": true,
    "resendOnRefresh": true,
    "templateScope": "local",
    "className": "",
    "x": 470,
    "y": 60,
    "wires": [[]]
  },
  {
    "id": "e395fac4f263f3d4",
    "type": "debug",
    "z": "69768f0c102c7a06",
    "name": "debug 5",
    "active": true,
    "tosidebar": true,
    "console": false,
    "tostatus": false,
    "complete": "false",
    "statusVal": "",
    "statusType": "auto",
    "x": 440,
    "y": 200,
    "wires": []
  },
  {
    "id": "d1fd3606d78fcb8f",
    "type": "mqtt-broker",
    "name": "Local MQTT Broker",
    "broker": "192.168.68.55",
    "port": "1883",
    "clientid": "",
    "autoConnect": true,
    "usetls": false,
    "protocolVersion": "4",
    "keepalive": "60",
    "cleansession": true,
    "autoUnsubscribe": true,
    "birthTopic": "",
    "birthQos": "0",
    "birthRetain": "false",
    "birthPayload": "",
    "birthMsg": {},
    "closeTopic": "",
    "closeQos": "0",
    "closeRetain": "false",
    "closePayload": "",
    "closeMsg": {},
    "willTopic": "",
    "willQos": "0",
    "willRetain": "false",
    "willPayload": "",
    "willMsg": {},
    "userProps": "",
    "sessionExpiry": ""
  },
  {
    "id": "7b5548eb75bbd6d1",
    "type": "ui_group",
    "name": "RFID Lock",
    "tab": "204c1aeb514b7ec1",
    "order": 1,
    "disp": true,
    "width": 6,
    "collapse": false,
    "className": ""
  },
  {
    "id": "204c1aeb514b7ec1",
    "type": "ui_tab",
    "name": "RFID Lock",
    "icon": "dashboard",
    "disabled": false,
    "hidden": false
  }
]
